json_dataclass_io_hooks/__init__.py
json_dataclass_io_hooks/json_dataclass_io_hooks.py
json_dataclass_io_hooks/tests/__init__.py
json_dataclass_io_hooks/tests/test_json_dataclass_io_hooks.py
json_dataclass_io_hooks-0.1.dist-info/LICENSE
json_dataclass_io_hooks-0.1.dist-info/METADATA
json_dataclass_io_hooks-0.1.dist-info/WHEEL
json_dataclass_io_hooks-0.1.dist-info/top_level.txt
json_dataclass_io_hooks-0.1.dist-info/RECORD
