Metadata-Version: 2.1
Name: json-dataclass-io-hooks
Version: 0.1
Summary: JSON encoder/decoder hooks for Python dataclasses
Home-page: https://github.com/datalyticsbe/json_dataclass_io_hooks/
Author: Datalytics BVBA
Author-email: datalyticsbe@gmail.com
License: MIT
Keywords: JSON,dataclass,dataclasses,save,load,store,hooks,convert,dict
Platform: UNKNOWN
Classifier: Development Status :: 3 - Alpha
Classifier: Intended Audience :: Developers
Classifier: Programming Language :: Python :: 3
Classifier: Programming Language :: Python :: 3.7
Requires-Python: >=3.7
